setup.py
src/MongoDBLibrary/__init__.py
src/MongoDBLibrary/mongo_connection_manager.py
src/MongoDBLibrary/mongoquery.py
src/MongoDBLibrary/version.py
src/robotframework_mongodblibrary.egg-info/PKG-INFO
src/robotframework_mongodblibrary.egg-info/SOURCES.txt
src/robotframework_mongodblibrary.egg-info/dependency_links.txt
src/robotframework_mongodblibrary.egg-info/requires.txt
src/robotframework_mongodblibrary.egg-info/top_level.txt