Metadata-Version: 1.0
Name: robotframework-mongodblibrary
Version: 0.3.4
Summary: Mongo Database utility library for Robot Framework
Home-page: https://github.com/iPlantCollaborativeOpenSource
Author: Jerry Schneider
Author-email: jerry@iplantcollaborative.org
License: UNKNOWN
Platform: UNKNOWN
